amicus_interfaces/__init__.py
amicus_interfaces/interfaces.py
amicus_interfaces-0.1.1.dist-info/METADATA
amicus_interfaces-0.1.1.dist-info/WHEEL
amicus_interfaces-0.1.1.dist-info/top_level.txt
amicus_interfaces-0.1.1.dist-info/RECORD
