Metadata-Version: 2.1
Name: amicus_interfaces
Version: 0.1.1
Summary: Un package pour les interfaces communes d'amicus.
Author: Christian Mauceri
Author-email: christian@example.com
Classifier: Programming Language :: Python :: 3
Classifier: License :: OSI Approved :: MIT License
Classifier: Operating System :: OS Independent
Requires-Python: >=3.6
